{
  "symbol": "7780",
  "generated_at": "2026-01-26T01:52:30.323006",
  "data_range": {
    "start": "2025-09-30",
    "end": "2026-01-23",
    "count": 73
  },
  "candles": [
    {
      "date": "2025-09-30",
      "open": 192.0,
      "high": 200.0,
      "low": 186.0,
      "close": 198.0,
      "volume": 503374
    },
    {
      "date": "2025-10-01",
      "open": 198.0,
      "high": 198.0,
      "low": 190.0,
      "close": 190.5,
      "volume": 411346
    },
    {
      "date": "2025-10-02",
      "open": 190.5,
      "high": 194.5,
      "low": 188.5,
      "close": 191.5,
      "volume": 439706
    },
    {
      "date": "2025-10-03",
      "open": 190.5,
      "high": 191.5,
      "low": 187.0,
      "close": 188.0,
      "volume": 349149
    },
    {
      "date": "2025-10-07",
      "open": 187.5,
      "high": 189.5,
      "low": 183.0,
      "close": 189.5,
      "volume": 522078
    },
    {
      "date": "2025-10-08",
      "open": 189.0,
      "high": 190.0,
      "low": 185.0,
      "close": 189.0,
      "volume": 258004
    },
    {
      "date": "2025-10-09",
      "open": 188.0,
      "high": 190.5,
      "low": 185.0,
      "close": 188.0,
      "volume": 302842
    },
    {
      "date": "2025-10-13",
      "open": 178.0,
      "high": 185.5,
      "low": 178.0,
      "close": 184.5,
      "volume": 291171
    },
    {
      "date": "2025-10-14",
      "open": 184.5,
      "high": 192.5,
      "low": 184.0,
      "close": 184.0,
      "volume": 453045
    },
    {
      "date": "2025-10-15",
      "open": 185.0,
      "high": 189.0,
      "low": 182.0,
      "close": 187.5,
      "volume": 248632
    },
    {
      "date": "2025-10-16",
      "open": 188.0,
      "high": 189.5,
      "low": 185.0,
      "close": 186.0,
      "volume": 260657
    },
    {
      "date": "2025-10-17",
      "open": 186.0,
      "high": 187.5,
      "low": 181.0,
      "close": 183.0,
      "volume": 373155
    },
    {
      "date": "2025-10-20",
      "open": 184.5,
      "high": 184.5,
      "low": 180.5,
      "close": 181.0,
      "volume": 221399
    },
    {
      "date": "2025-10-21",
      "open": 181.5,
      "high": 185.0,
      "low": 180.5,
      "close": 182.5,
      "volume": 305626
    },
    {
      "date": "2025-10-22",
      "open": 181.5,
      "high": 183.5,
      "low": 180.5,
      "close": 181.5,
      "volume": 229119
    },
    {
      "date": "2025-10-23",
      "open": 180.0,
      "high": 180.5,
      "low": 173.0,
      "close": 174.5,
      "volume": 612684
    },
    {
      "date": "2025-10-27",
      "open": 175.0,
      "high": 175.5,
      "low": 167.0,
      "close": 167.5,
      "volume": 703266
    },
    {
      "date": "2025-10-28",
      "open": 166.0,
      "high": 170.0,
      "low": 160.0,
      "close": 165.0,
      "volume": 1066919
    },
    {
      "date": "2025-10-29",
      "open": 165.5,
      "high": 168.0,
      "low": 162.0,
      "close": 167.5,
      "volume": 302488
    },
    {
      "date": "2025-10-30",
      "open": 165.0,
      "high": 167.0,
      "low": 163.0,
      "close": 165.5,
      "volume": 197796
    },
    {
      "date": "2025-10-31",
      "open": 167.5,
      "high": 175.0,
      "low": 167.5,
      "close": 170.0,
      "volume": 481294
    },
    {
      "date": "2025-11-03",
      "open": 171.5,
      "high": 187.0,
      "low": 171.5,
      "close": 187.0,
      "volume": 1282387
    },
    {
      "date": "2025-11-04",
      "open": 189.0,
      "high": 192.5,
      "low": 184.0,
      "close": 184.5,
      "volume": 1117284
    },
    {
      "date": "2025-11-05",
      "open": 181.0,
      "high": 184.0,
      "low": 178.0,
      "close": 184.0,
      "volume": 333433
    },
    {
      "date": "2025-11-06",
      "open": 185.5,
      "high": 191.5,
      "low": 182.0,
      "close": 187.0,
      "volume": 485409
    },
    {
      "date": "2025-11-07",
      "open": 189.0,
      "high": 189.0,
      "low": 184.0,
      "close": 185.0,
      "volume": 311664
    },
    {
      "date": "2025-11-10",
      "open": 184.0,
      "high": 184.0,
      "low": 177.0,
      "close": 180.0,
      "volume": 343198
    },
    {
      "date": "2025-11-11",
      "open": 180.0,
      "high": 180.0,
      "low": 175.0,
      "close": 176.0,
      "volume": 294068
    },
    {
      "date": "2025-11-12",
      "open": 176.0,
      "high": 177.5,
      "low": 172.5,
      "close": 173.0,
      "volume": 226207
    },
    {
      "date": "2025-11-13",
      "open": 172.5,
      "high": 184.5,
      "low": 171.0,
      "close": 182.0,
      "volume": 406751
    },
    {
      "date": "2025-11-14",
      "open": 180.0,
      "high": 184.5,
      "low": 178.5,
      "close": 183.0,
      "volume": 285652
    },
    {
      "date": "2025-11-17",
      "open": 184.0,
      "high": 187.0,
      "low": 181.0,
      "close": 183.5,
      "volume": 350664
    },
    {
      "date": "2025-11-18",
      "open": 183.5,
      "high": 184.5,
      "low": 176.0,
      "close": 178.5,
      "volume": 425520
    },
    {
      "date": "2025-11-19",
      "open": 180.5,
      "high": 180.5,
      "low": 173.0,
      "close": 173.0,
      "volume": 181756
    },
    {
      "date": "2025-11-20",
      "open": 176.5,
      "high": 185.0,
      "low": 176.5,
      "close": 183.5,
      "volume": 371418
    },
    {
      "date": "2025-11-21",
      "open": 180.0,
      "high": 182.0,
      "low": 178.5,
      "close": 181.0,
      "volume": 270356
    },
    {
      "date": "2025-11-24",
      "open": 184.0,
      "high": 186.5,
      "low": 180.0,
      "close": 182.0,
      "volume": 333355
    },
    {
      "date": "2025-11-25",
      "open": 182.0,
      "high": 185.5,
      "low": 180.0,
      "close": 180.0,
      "volume": 308822
    },
    {
      "date": "2025-11-26",
      "open": 181.0,
      "high": 184.0,
      "low": 180.0,
      "close": 180.0,
      "volume": 156802
    },
    {
      "date": "2025-11-27",
      "open": 180.5,
      "high": 181.0,
      "low": 177.5,
      "close": 179.0,
      "volume": 160325
    },
    {
      "date": "2025-11-28",
      "open": 181.0,
      "high": 184.0,
      "low": 179.0,
      "close": 184.0,
      "volume": 221872
    },
    {
      "date": "2025-12-01",
      "open": 183.0,
      "high": 187.5,
      "low": 181.0,
      "close": 186.0,
      "volume": 289409
    },
    {
      "date": "2025-12-02",
      "open": 184.0,
      "high": 192.5,
      "low": 184.0,
      "close": 190.0,
      "volume": 467907
    },
    {
      "date": "2025-12-03",
      "open": 190.5,
      "high": 193.0,
      "low": 187.0,
      "close": 188.5,
      "volume": 321090
    },
    {
      "date": "2025-12-04",
      "open": 190.0,
      "high": 190.0,
      "low": 183.0,
      "close": 184.0,
      "volume": 203418
    },
    {
      "date": "2025-12-05",
      "open": 184.0,
      "high": 187.0,
      "low": 183.0,
      "close": 186.0,
      "volume": 103973
    },
    {
      "date": "2025-12-08",
      "open": 188.0,
      "high": 192.0,
      "low": 186.5,
      "close": 189.5,
      "volume": 315003
    },
    {
      "date": "2025-12-09",
      "open": 189.5,
      "high": 189.5,
      "low": 179.0,
      "close": 179.0,
      "volume": 559330
    },
    {
      "date": "2025-12-10",
      "open": 180.5,
      "high": 181.5,
      "low": 176.0,
      "close": 177.0,
      "volume": 335102
    },
    {
      "date": "2025-12-11",
      "open": 180.0,
      "high": 182.5,
      "low": 173.5,
      "close": 175.0,
      "volume": 387763
    },
    {
      "date": "2025-12-12",
      "open": 175.0,
      "high": 176.0,
      "low": 171.0,
      "close": 171.5,
      "volume": 233909
    },
    {
      "date": "2025-12-15",
      "open": 169.5,
      "high": 171.0,
      "low": 166.0,
      "close": 167.5,
      "volume": 333146
    },
    {
      "date": "2025-12-16",
      "open": 166.5,
      "high": 169.5,
      "low": 160.5,
      "close": 161.5,
      "volume": 387753
    },
    {
      "date": "2025-12-17",
      "open": 161.5,
      "high": 165.5,
      "low": 161.5,
      "close": 162.5,
      "volume": 164926
    },
    {
      "date": "2025-12-18",
      "open": 162.5,
      "high": 162.5,
      "low": 160.0,
      "close": 161.5,
      "volume": 135588
    },
    {
      "date": "2025-12-19",
      "open": 161.0,
      "high": 163.0,
      "low": 161.0,
      "close": 162.5,
      "volume": 59066
    },
    {
      "date": "2025-12-22",
      "open": 162.5,
      "high": 163.0,
      "low": 160.5,
      "close": 161.0,
      "volume": 153223
    },
    {
      "date": "2025-12-23",
      "open": 166.5,
      "high": 172.0,
      "low": 166.5,
      "close": 169.5,
      "volume": 309990
    },
    {
      "date": "2025-12-24",
      "open": 171.0,
      "high": 171.5,
      "low": 163.5,
      "close": 164.0,
      "volume": 332856
    },
    {
      "date": "2025-12-26",
      "open": 166.0,
      "high": 167.5,
      "low": 165.0,
      "close": 167.0,
      "volume": 125042
    },
    {
      "date": "2025-12-29",
      "open": 169.0,
      "high": 174.5,
      "low": 168.5,
      "close": 172.5,
      "volume": 529183
    },
    {
      "date": "2025-12-30",
      "open": 172.0,
      "high": 173.0,
      "low": 168.0,
      "close": 172.0,
      "volume": 250386
    },
    {
      "date": "2025-12-31",
      "open": 172.0,
      "high": 184.0,
      "low": 172.0,
      "close": 179.5,
      "volume": 638174
    },
    {
      "date": "2026-01-02",
      "open": 182.0,
      "high": 190.0,
      "low": 180.0,
      "close": 189.5,
      "volume": 884260
    },
    {
      "date": "2026-01-05",
      "open": 192.0,
      "high": 192.0,
      "low": 178.5,
      "close": 179.0,
      "volume": 744611
    },
    {
      "date": "2026-01-06",
      "open": 179.0,
      "high": 182.0,
      "low": 176.5,
      "close": 181.5,
      "volume": 326677
    },
    {
      "date": "2026-01-07",
      "open": 182.0,
      "high": 183.5,
      "low": 179.0,
      "close": 181.5,
      "volume": 261556
    },
    {
      "date": "2026-01-08",
      "open": 183.0,
      "high": 186.5,
      "low": 181.5,
      "close": 185.0,
      "volume": 523826
    },
    {
      "date": "2026-01-19",
      "open": 20.35,
      "high": 20.35,
      "low": 19.65,
      "close": 20.35,
      "volume": 34537186
    },
    {
      "date": "2026-01-20",
      "open": 22.35,
      "high": 22.35,
      "low": 22.35,
      "close": 22.35,
      "volume": 8682281
    },
    {
      "date": "2026-01-21",
      "open": 24.55,
      "high": 24.55,
      "low": 24.55,
      "close": 24.55,
      "volume": 9353709
    },
    {
      "date": "2026-01-22",
      "open": 27.0,
      "high": 27.0,
      "low": 24.85,
      "close": 27.0,
      "volume": 94598331
    },
    {
      "date": "2026-01-23",
      "open": 27.7,
      "high": 29.4,
      "low": 27.4,
      "close": 28.85,
      "volume": 74050065
    }
  ],
  "swing_points": [
    {
      "index": 7,
      "date": "2025-10-13",
      "type": "swing_low",
      "level": 178.0
    },
    {
      "index": 8,
      "date": "2025-10-14",
      "type": "swing_high",
      "level": 192.5
    },
    {
      "index": 17,
      "date": "2025-10-28",
      "type": "swing_low",
      "level": 160.0
    },
    {
      "index": 22,
      "date": "2025-11-04",
      "type": "swing_high",
      "level": 192.5
    },
    {
      "index": 29,
      "date": "2025-11-13",
      "type": "swing_low",
      "level": 171.0
    },
    {
      "index": 31,
      "date": "2025-11-17",
      "type": "swing_high",
      "level": 187.0
    },
    {
      "index": 43,
      "date": "2025-12-03",
      "type": "swing_high",
      "level": 193.0
    },
    {
      "index": 54,
      "date": "2025-12-18",
      "type": "swing_low",
      "level": 160.0
    },
    {
      "index": 64,
      "date": "2026-01-05",
      "type": "swing_high",
      "level": 192.0
    }
  ],
  "fvg": [
    {
      "index": 12,
      "date": "2025-10-20",
      "type": "bearish",
      "top": 185.0,
      "bottom": 184.5,
      "start_index": 10
    },
    {
      "index": 16,
      "date": "2025-10-27",
      "type": "bearish",
      "top": 180.5,
      "bottom": 175.5,
      "start_index": 14
    },
    {
      "index": 17,
      "date": "2025-10-28",
      "type": "bearish",
      "top": 173.0,
      "bottom": 170.0,
      "start_index": 15
    },
    {
      "index": 21,
      "date": "2025-11-03",
      "type": "bullish",
      "top": 171.5,
      "bottom": 167.0,
      "start_index": 19
    },
    {
      "index": 22,
      "date": "2025-11-04",
      "type": "bullish",
      "top": 184.0,
      "bottom": 175.0,
      "start_index": 20
    },
    {
      "index": 27,
      "date": "2025-11-11",
      "type": "bearish",
      "top": 184.0,
      "bottom": 180.0,
      "start_index": 25
    },
    {
      "index": 30,
      "date": "2025-11-14",
      "type": "bullish",
      "top": 178.5,
      "bottom": 177.5,
      "start_index": 28
    },
    {
      "index": 33,
      "date": "2025-11-19",
      "type": "bearish",
      "top": 181.0,
      "bottom": 180.5,
      "start_index": 31
    },
    {
      "index": 48,
      "date": "2025-12-10",
      "type": "bearish",
      "top": 186.5,
      "bottom": 181.5,
      "start_index": 46
    },
    {
      "index": 51,
      "date": "2025-12-15",
      "type": "bearish",
      "top": 173.5,
      "bottom": 171.0,
      "start_index": 49
    },
    {
      "index": 52,
      "date": "2025-12-16",
      "type": "bearish",
      "top": 171.0,
      "bottom": 169.5,
      "start_index": 50
    },
    {
      "index": 53,
      "date": "2025-12-17",
      "type": "bearish",
      "top": 166.0,
      "bottom": 165.5,
      "start_index": 51
    },
    {
      "index": 57,
      "date": "2025-12-23",
      "type": "bullish",
      "top": 166.5,
      "bottom": 163.0,
      "start_index": 55
    },
    {
      "index": 58,
      "date": "2025-12-24",
      "type": "bullish",
      "top": 163.5,
      "bottom": 163.0,
      "start_index": 56
    },
    {
      "index": 61,
      "date": "2025-12-30",
      "type": "bullish",
      "top": 168.0,
      "bottom": 167.5,
      "start_index": 59
    },
    {
      "index": 63,
      "date": "2026-01-02",
      "type": "bullish",
      "top": 180.0,
      "bottom": 173.0,
      "start_index": 61
    },
    {
      "index": 68,
      "date": "2026-01-19",
      "type": "bearish",
      "top": 179.0,
      "bottom": 20.35,
      "start_index": 66
    },
    {
      "index": 69,
      "date": "2026-01-20",
      "type": "bearish",
      "top": 181.5,
      "bottom": 22.35,
      "start_index": 67
    },
    {
      "index": 70,
      "date": "2026-01-21",
      "type": "bullish",
      "top": 24.55,
      "bottom": 20.35,
      "start_index": 68
    },
    {
      "index": 71,
      "date": "2026-01-22",
      "type": "bullish",
      "top": 24.85,
      "bottom": 22.35,
      "start_index": 69
    },
    {
      "index": 72,
      "date": "2026-01-23",
      "type": "bullish",
      "top": 27.4,
      "bottom": 24.55,
      "start_index": 70
    }
  ],
  "bos_choch": [
    {
      "index": 68,
      "date": "2026-01-19",
      "type": "BOS",
      "direction": "bearish",
      "level": 160.0
    }
  ],
  "setup": {
    "direction": "SHORT",
    "entry_zone": [
      191.04,
      192.96
    ],
    "sl": 193.0,
    "tp": 160.0,
    "rr": 32.0,
    "latest_close": 28.85
  }
}